{"accountsList":[{"accountId":1002,"balance":10.0,"accountType":"Savings","openDate":"08/02/2018","status":"Active","customerId":9002},{"accountId":1003,"balance":1000.22,"accountType":"Savings","openDate":"08/02/2018","status":"Active","customerId":9002},{"accountId":1005,"balance":99.0,"accountType":"Savings","status":"Opened","customerId":9005},{"accountId":1006,"balance":99.0,"accountType":"Savings","status":"Opened","customerId":9005},{"accountId":1007,"balance":99.0,"accountType":"Savings","status":"Opened","customerId":9005},{"accountId":1008,"balance":99.0,"accountType":"Savings","status":"Opened","customerId":9005},{"accountId":1009,"balance":99.0,"accountType":"Savings","status":"Opened","customerId":9005},{"accountId":1010,"balance":99.0,"accountType":"Savings","status":"Opened","customerId":9005},{"accountId":1011,"balance":99.0,"accountType":"Savings","status":"Opened","customerId":9005},{"accountId":1012,"balance":99.0,"accountType":"Savings","status":"Opened","customerId":9005},{"accountId":1013,"balance":99.0,"accountType":"Savings","status":"Opened","customerId":9005},{"accountId":1014,"balance":99.0,"accountType":"Savings","status":"Opened","customerId":9005},{"accountId":1015,"balance":99.0,"accountType":"Savings","status":"Opened","customerId":9005},{"accountId":1016,"balance":99.0,"accountType":"Savings","status":"Opened","customerId":9005},{"accountId":1017,"balance":99.0,"accountType":"Savings","status":"Opened","customerId":9005},{"accountId":1004,"balance":1000.0,"accountType":"Savings","openDate":"08/02/2018","status":"Active","customerId":9004},{"accountId":1004,"balance":99.0,"accountType":"Current","status":"Opened","customerId":9005},{"accountId":1018,"balance":1500.0,"accountType":"Savings","status":"Active","customerId":9004}],"accountSequenceNumber":1018}